cmssdk
