Metadata-Version: 1.1
Name: cmssdk
Version: 0.6.7
Summary: Ridi CMS SDK
Home-page: https://github.com/ridi/cms-sdk
Author: UNKNOWN
Author-email: UNKNOWN
License: UNKNOWN
Keywords: cmssdk,ridi,ridibooks
Platform: UNKNOWN
Classifier: License :: OSI Approved :: MIT License
Classifier: Programming Language :: Python :: 3
